email_scraper_from_html/__init__.py
email_scraper_from_html/email_scraping.py
email_scraper_from_html-1.1.data/scripts/scrape
email_scraper_from_html-1.1.dist-info/DESCRIPTION.rst
email_scraper_from_html-1.1.dist-info/METADATA
email_scraper_from_html-1.1.dist-info/RECORD
email_scraper_from_html-1.1.dist-info/WHEEL
email_scraper_from_html-1.1.dist-info/metadata.json
email_scraper_from_html-1.1.dist-info/top_level.txt
