Metadata-Version: 2.0
Name: email-scraper-from-html
Version: 1.1
Summary: Generates list of emails scraped from a given HTML file
Home-page: https://github.com/jonjonrankin/email_scraper_from_html
Author: jonjonrankin
Author-email: jonathan@skoller.co
License: MIT
Platform: UNKNOWN
Requires-Python: >=3
Requires-Dist: argparse
Requires-Dist: bs4
Requires-Dist: lxml
Requires-Dist: pandas
